recombinator/__init__.py
recombinator/block_bootstrap.py
recombinator/bootstrap_cocos.py
recombinator/iid_bootstrap.py
recombinator/log_returns.py
recombinator/numba_rng_tools.py
recombinator/optimal_block_length.py
recombinator/statistics.py
recombinator/tapered_block_bootstrap.py
recombinator/utilities.py
recombinator/tests/__init__.py
recombinator/tests/conftest.py
recombinator/tests/rng_link_tools.py
recombinator/tests/test_aggregate_multi_dimensional_log_returns.py
recombinator/tests/test_block_bootstrap/__init__.py
recombinator/tests/test_block_bootstrap/test_block_bootstrap.py
recombinator/tests/test_iid_boostrap/__init__.py
recombinator/tests/test_iid_boostrap/test_iid_bootstrap.py
recombinator-0.0.6.1.dist-info/LICENSE
recombinator-0.0.6.1.dist-info/METADATA
recombinator-0.0.6.1.dist-info/WHEEL
recombinator-0.0.6.1.dist-info/top_level.txt
recombinator-0.0.6.1.dist-info/RECORD
