Metadata-Version: 2.1
Name: recombinator
Version: 0.0.6.1
Summary: Recombinator - Statistical Resampling in Python
Home-page: https://github.com/InvestmentSystems/recombinator
Author: Michael Christoph Nowotny
Author-email: nowotnym@gmail.com
License: MIT
Platform: UNKNOWN
Classifier: License :: OSI Approved :: MIT License
Classifier: Programming Language :: Python
Classifier: Programming Language :: Python :: 3
Classifier: Programming Language :: Python :: 3.6
Classifier: Programming Language :: Python :: 3.7
Classifier: Programming Language :: Python :: 3.8
Classifier: Programming Language :: Python :: 3.9
Classifier: Programming Language :: Python :: Implementation :: CPython
Requires-Python: >=3.6.0
Requires-Dist: cocos
Requires-Dist: numba
Requires-Dist: numpy
Requires-Dist: pandas
Requires-Dist: scipy
Requires-Dist: pytest
